multilang/__init__.py
multilang/main.py
Python3_MultiLang-1.1.dist-info/METADATA
Python3_MultiLang-1.1.dist-info/WHEEL
Python3_MultiLang-1.1.dist-info/top_level.txt
Python3_MultiLang-1.1.dist-info/RECORD
