Metadata-Version: 2.1
Name: Python3-MultiLang
Version: 1.1
Summary: ML is a Library for Multi Language support in Python.
Home-page: https://github.com/DDavid701/python_multilang
Author: DDavid701
Author-email: ddavid701@gmail.com
Classifier: Programming Language :: Python :: 3
Classifier: License :: OSI Approved :: MIT License
Classifier: Operating System :: OS Independent
Requires-Python: >=3.10
